spectrometers
