Metadata-Version: 1.0
Name: spectrometers
Version: 0.0.3
Summary: API for spectrophotometers (pre-alpha)
Home-page: https://github.com/kanzure/python-spectrometers
Author: Bryan Bishop
Author-email: kanzure@gmail.com
License: BSD
Platform: any
Classifier: Natural Language :: English
Classifier: License :: OSI Approved :: BSD License
Classifier: Operating System :: OS Independent
Classifier: Programming Language :: Python
